Metadata-Version: 2.1
Name: nonebot-plugin-unoconv
Version: 0.5.6
Summary: nonebot_plugin about use unoconv
Home-page: https://github.com/Zeta-qixi/nonebot-plugin-unoconv/
Author: Zeta
Author-email: 
License: MIT Licence
Platform: UNKNOWN
License-File: LICENSE
